{
  "baseUrl": "http://localhost:8080/",
  "integrationFolder": "tests/cypress/integration",
  "screenshotsFolder": "tests/cypress/screenshots",
  "videosFolder": "tests/cypress/videos",
  "supportFile": "tests/cypress/support/index.js",
  "fixturesFolder": "tests/cypress/fixtures",
  "pluginsFile": "tests/cypress/plugins/index.js",
  "chromeWebSecurity": false,
  "scrollBehavior": "center",
  "video": true,
  "retries": {
    "runMode": 2,
    "openMode": 0
  },
  "viewportWidth": 1280,
  "viewportHeight": 1024
}
