{
	"info": {
		"_postman_id": "4900b560-17a3-4b92-9216-e9db5e91fee5",
		"name": "Sessions (Okta API)",
		"description": "The [Okta Session API](/docs/api/rest/sessions.html) provides operations to create and manage authentication sessions with your Okta organization.",
		"schema": "https://schema.getpostman.com/json/collection/v2.1.0/collection.json"
	},
	"item": [
		{
			"name": "Create Session with Session Token",
			"request": {
				"method": "POST",
				"header": [
					{
						"key": "Accept",
						"value": "application/json"
					},
					{
						"key": "Content-Type",
						"value": "application/json"
					},
					{
						"key": "Authorization",
						"value": "SSWS {{apikey}}"
					}
				],
				"body": {
					"mode": "raw",
					"raw": "{\n  \"sessionToken\": \"{{sessionToken}}\"\n}"
				},
				"url": {
					"raw": "{{url}}/api/v1/sessions?additionalFields=cookieToken",
					"host": [
						"{{url}}"
					],
					"path": [
						"api",
						"v1",
						"sessions"
					],
					"query": [
						{
							"key": "additionalFields",
							"value": "cookieToken"
						}
					]
				}
			},
			"response": []
		},
		{
			"name": "Set Session with Token Redirect",
			"request": {
				"method": "GET",
				"header": [
					{
						"key": "Accept",
						"value": "*/*"
					}
				],
				"url": {
					"raw": "{{url}}/login/sessionCookieRedirect?token={{sessionToken}}&redirectUrl={{redirectUrl}}",
					"host": [
						"{{url}}"
					],
					"path": [
						"login",
						"sessionCookieRedirect"
					],
					"query": [
						{
							"key": "token",
							"value": "{{sessionToken}}"
						},
						{
							"key": "redirectUrl",
							"value": "{{redirectUrl}}"
						}
					]
				}
			},
			"response": []
		},
		{
			"name": "Extend Session",
			"request": {
				"method": "PUT",
				"header": [
					{
						"key": "Accept",
						"value": "application/json"
					},
					{
						"key": "Content-Type",
						"value": "application/json"
					},
					{
						"key": "Authorization",
						"value": "SSWS {{apikey}}"
					}
				],
				"body": {
					"mode": "raw",
					"raw": ""
				},
				"url": {
					"raw": "{{url}}/api/v1/sessions/{{sessionId}}",
					"host": [
						"{{url}}"
					],
					"path": [
						"api",
						"v1",
						"sessions",
						"{{sessionId}}"
					]
				}
			},
			"response": []
		},
		{
			"name": "Validate Session",
			"request": {
				"method": "GET",
				"header": [
					{
						"key": "Accept",
						"value": "application/json"
					},
					{
						"key": "Content-Type",
						"value": "application/json"
					},
					{
						"key": "Authorization",
						"value": "SSWS {{apikey}}"
					}
				],
				"url": {
					"raw": "{{url}}/api/v1/sessions/{{sessionId}}",
					"host": [
						"{{url}}"
					],
					"path": [
						"api",
						"v1",
						"sessions",
						"{{sessionId}}"
					]
				}
			},
			"response": []
		},
		{
			"name": "Clear Session",
			"request": {
				"method": "DELETE",
				"header": [
					{
						"key": "Accept",
						"value": "application/json"
					},
					{
						"key": "Content-Type",
						"value": "application/json"
					},
					{
						"key": "Authorization",
						"value": "SSWS {{apikey}}"
					}
				],
				"body": {
					"mode": "raw",
					"raw": ""
				},
				"url": {
					"raw": "{{url}}/api/v1/sessions/{{sessionId}}",
					"host": [
						"{{url}}"
					],
					"path": [
						"api",
						"v1",
						"sessions",
						"{{sessionId}}"
					]
				}
			},
			"response": []
		},
		{
			"name": "Get Current Session",
			"request": {
				"method": "GET",
				"header": [
					{
						"key": "Accept",
						"value": "application/json"
					},
					{
						"key": "Content-Type",
						"value": "application/json"
					}
				],
				"url": {
					"raw": "{{url}}/api/v1/sessions/me",
					"host": [
						"{{url}}"
					],
					"path": [
						"api",
						"v1",
						"sessions",
						"me"
					]
				},
				"description": "Get session information for the current user. Use this method in a browser based application to determine if the user is logged in.\n\n> The session `id` returned from `/sessions/me` is an `externalId` and can only be used with the **Refresh Session** endpoint."
			},
			"response": []
		},
		{
			"name": "Close Current Session",
			"request": {
				"method": "DELETE",
				"header": [
					{
						"key": "Accept",
						"value": "application/json"
					},
					{
						"key": "Content-Type",
						"value": "application/json"
					}
				],
				"body": {
					"mode": "formdata",
					"formdata": []
				},
				"url": {
					"raw": "{{url}}/api/v1/sessions/me",
					"host": [
						"{{url}}"
					],
					"path": [
						"api",
						"v1",
						"sessions",
						"me"
					]
				}
			},
			"response": []
		},
		{
			"name": "Refresh Session",
			"request": {
				"method": "POST",
				"header": [
					{
						"key": "Accept",
						"value": "application/json"
					},
					{
						"key": "Content-Type",
						"value": "application/json"
					}
				],
				"body": {
					"mode": "formdata",
					"formdata": []
				},
				"url": {
					"raw": "{{url}}/api/v1/sessions/{{externalId}}/lifecycle/refresh",
					"host": [
						"{{url}}"
					],
					"path": [
						"api",
						"v1",
						"sessions",
						"{{externalId}}",
						"lifecycle",
						"refresh"
					]
				}
			},
			"response": []
		}
	]
}